odoo/addons/helpdesk_split_and_merge/CHANGELOG.md
odoo/addons/helpdesk_split_and_merge/README.rst
odoo/addons/helpdesk_split_and_merge/__init__.py
odoo/addons/helpdesk_split_and_merge/__manifest__.py
odoo/addons/helpdesk_split_and_merge/i18n/ca_ES.po
odoo/addons/helpdesk_split_and_merge/i18n/es.po
odoo/addons/helpdesk_split_and_merge/i18n/helpdesk_split_and_merge.pot
odoo/addons/helpdesk_split_and_merge/models/__init__.py
odoo/addons/helpdesk_split_and_merge/models/helpdesk_ticket.py
odoo/addons/helpdesk_split_and_merge/models/settings.py
odoo/addons/helpdesk_split_and_merge/security/ir.model.access.csv
odoo/addons/helpdesk_split_and_merge/setup/.setuptools-odoo-make-default-ignore
odoo/addons/helpdesk_split_and_merge/setup/README
odoo/addons/helpdesk_split_and_merge/static/description/icon.png
odoo/addons/helpdesk_split_and_merge/tests/__init__.py
odoo/addons/helpdesk_split_and_merge/tests/test_merge_tickets.py
odoo/addons/helpdesk_split_and_merge/tests/test_split_tickets.py
odoo/addons/helpdesk_split_and_merge/views/helpdesk_ticket_merge_view.xml
odoo/addons/helpdesk_split_and_merge/views/helpdesk_ticket_split_view.xml
odoo/addons/helpdesk_split_and_merge/views/res_config_settings.xml
odoo/addons/helpdesk_split_and_merge/wizards/__init__.py
odoo/addons/helpdesk_split_and_merge/wizards/helpdesk_ticket_merge.py
odoo/addons/helpdesk_split_and_merge/wizards/helpdesk_ticket_split.py
odoo/addons/helpdesk_split_and_merge/wizards/merge_ticket_wizard.xml
odoo/addons/helpdesk_split_and_merge/wizards/split_ticket_wizard.xml
odoo_addon_helpdesk_split_and_merge-16.0.1.0.0.dist-info/METADATA
odoo_addon_helpdesk_split_and_merge-16.0.1.0.0.dist-info/WHEEL
odoo_addon_helpdesk_split_and_merge-16.0.1.0.0.dist-info/top_level.txt
odoo_addon_helpdesk_split_and_merge-16.0.1.0.0.dist-info/RECORD
