Metadata-Version: 2.1
Name: odoo-addon-helpdesk-split-and-merge
Version: 16.0.1.0.0
Summary: Split and Merge Helpdesk Tickets
Home-page: https://gitlab.com/somitcoop/erp-research/odoo-helpdesk
Author: Som It Cooperatiu SCCL
License: AGPL-3
Classifier: Programming Language :: Python
Classifier: Framework :: Odoo
Classifier: Framework :: Odoo :: 16.0
Classifier: License :: OSI Approved :: GNU Affero General Public License v3
Requires-Python: >=3.10
Requires-Dist: odoo-addon-helpdesk-mgmt <16.1dev,>=16.0dev
Requires-Dist: odoo <16.1dev,>=16.0a
